pythonventsampleproject-1.0.0.data/data/my_data/data_file
sample/__init__.py
sample/package_data.dat
sample/simple.py
pythonventsampleproject-1.0.0.dist-info/LICENSE.txt
pythonventsampleproject-1.0.0.dist-info/METADATA
pythonventsampleproject-1.0.0.dist-info/WHEEL
pythonventsampleproject-1.0.0.dist-info/entry_points.txt
pythonventsampleproject-1.0.0.dist-info/top_level.txt
pythonventsampleproject-1.0.0.dist-info/RECORD
