Metadata-Version: 2.1
Name: pythonventsampleproject
Version: 1.0.0
Summary: A sample Python project
Home-page: https://github.com/
Author: me
Author-email: me@me.com
License: UNKNOWN
Project-URL: Bug Reports, https://github.com/
Project-URL: Funding, https://donate.pypi.org
Project-URL: Say Thanks!, http://saythanks.io
Project-URL: Source, https://github.com/
Keywords: keyword
Platform: UNKNOWN
Classifier: Development Status :: 3 - Alpha
Classifier: Intended Audience :: Developers
Classifier: Topic :: Software Development :: Build Tools
Classifier: License :: OSI Approved :: MIT License
Classifier: Programming Language :: Python :: 3
Classifier: Programming Language :: Python :: 3.5
Classifier: Programming Language :: Python :: 3.6
Classifier: Programming Language :: Python :: 3.7
Classifier: Programming Language :: Python :: 3.8
Classifier: Programming Language :: Python :: 3 :: Only
Requires-Python: >=3.5, <4
License-File: LICENSE.txt
Requires-Dist: peppercorn
Provides-Extra: dev
Requires-Dist: check-manifest ; extra == 'dev'
Provides-Extra: test
Requires-Dist: coverage ; extra == 'test'
